midiloop/__init__.py
midiloop/__main__.py
midiloop-0.0.1.dist-info/LICENSE
midiloop-0.0.1.dist-info/METADATA
midiloop-0.0.1.dist-info/WHEEL
midiloop-0.0.1.dist-info/entry_points.txt
midiloop-0.0.1.dist-info/top_level.txt
midiloop-0.0.1.dist-info/RECORD
