Metadata-Version: 2.1
Name: midiloop
Version: 0.0.1
Summary: A small utility that runs a virtual MIDI loopback device
License: MIT License
Project-URL: Homepage, https://github.com/fwcd/midiloop
Project-URL: Repository, https://github.com/fwcd/midiloop
Keywords: midi
Classifier: Topic :: Utilities
Classifier: Topic :: Multimedia :: Sound/Audio :: MIDI
Requires-Python: >=3.9
License-File: LICENSE
Requires-Dist: mido <2,>=1.3
Requires-Dist: python-rtmidi <2,>=1.5
